django_amazon-0.0.2.dist-info/DESCRIPTION.rst
django_amazon-0.0.2.dist-info/METADATA
django_amazon-0.0.2.dist-info/RECORD
django_amazon-0.0.2.dist-info/WHEEL
django_amazon-0.0.2.dist-info/metadata.json
django_amazon-0.0.2.dist-info/top_level.txt
migrations/__init__.py
