Metadata-Version: 2.0
Name: django-amazon
Version: 0.0.2
Summary: Amazon Django app
Home-page: https://github.com/raiski/django-amazon
Author: Andrei Raiski
Author-email: 7050743@gmail.com
License: MIT License
Platform: UNKNOWN
